remap_ville_plugin/__init__.py
remap_ville_plugin/copy_archetypes.py
remap_ville_plugin/mapping_CONSTRUCTION_STANDARD.xlsx
remap_ville_plugin/mapping_USE_TYPE.xlsx
remap_ville_plugin/plugin.config
remap_ville_plugin/remap.py
remap_ville_plugin/remap_construction_standards.py
remap_ville_plugin/remap_use_types.py
remap_ville_plugin/scripts.yml
remap_ville_plugin/test_use_type_pattern_matching.py
remap_ville_plugin/CH_ReMaP/archetypes/RRL_2040_BAU/CONSTRUCTION_STANDARD.xlsx
remap_ville_plugin/CH_ReMaP/archetypes/RRL_2040_BAU/use_types/COOLROOM.csv
remap_ville_plugin/CH_ReMaP/archetypes/RRL_2040_BAU/use_types/FOODSTORE.csv
remap_ville_plugin/CH_ReMaP/archetypes/RRL_2040_BAU/use_types/GYM.csv
remap_ville_plugin/CH_ReMaP/archetypes/RRL_2040_BAU/use_types/HOSPITAL.csv
remap_ville_plugin/CH_ReMaP/archetypes/RRL_2040_BAU/use_types/HOTEL.csv
remap_ville_plugin/CH_ReMaP/archetypes/RRL_2040_BAU/use_types/INDUSTRIAL.csv
remap_ville_plugin/CH_ReMaP/archetypes/RRL_2040_BAU/use_types/LAB.csv
remap_ville_plugin/CH_ReMaP/archetypes/RRL_2040_BAU/use_types/LIBRARY.csv
remap_ville_plugin/CH_ReMaP/archetypes/RRL_2040_BAU/use_types/MULTI_RES.csv
remap_ville_plugin/CH_ReMaP/archetypes/RRL_2040_BAU/use_types/MUSEUM.csv
remap_ville_plugin/CH_ReMaP/archetypes/RRL_2040_BAU/use_types/OFFICE.csv
remap_ville_plugin/CH_ReMaP/archetypes/RRL_2040_BAU/use_types/PARKING.csv
remap_ville_plugin/CH_ReMaP/archetypes/RRL_2040_BAU/use_types/RESTAURANT.csv
remap_ville_plugin/CH_ReMaP/archetypes/RRL_2040_BAU/use_types/RETAIL.csv
remap_ville_plugin/CH_ReMaP/archetypes/RRL_2040_BAU/use_types/SCHOOL.csv
remap_ville_plugin/CH_ReMaP/archetypes/RRL_2040_BAU/use_types/SERVERROOM.csv
remap_ville_plugin/CH_ReMaP/archetypes/RRL_2040_BAU/use_types/SINGLE_RES.csv
remap_ville_plugin/CH_ReMaP/archetypes/RRL_2040_BAU/use_types/SWIMMING.csv
remap_ville_plugin/CH_ReMaP/archetypes/RRL_2040_BAU/use_types/UNIVERSITY.csv
remap_ville_plugin/CH_ReMaP/archetypes/RRL_2040_BAU/use_types/USE_TYPE_PROPERTIES.xlsx
cea_remap_ville_plugin-1.0.0.dist-info/LICENSE
cea_remap_ville_plugin-1.0.0.dist-info/METADATA
cea_remap_ville_plugin-1.0.0.dist-info/WHEEL
cea_remap_ville_plugin-1.0.0.dist-info/top_level.txt
cea_remap_ville_plugin-1.0.0.dist-info/RECORD
