Metadata-Version: 2.1
Name: cea-remap-ville-plugin
Version: 1.0.0
Summary: A CEA plugin for the ReMaP / VILLE project
Home-page: https://github.com/architecture-building-systems/cea-remap-ville-plugin
Author: Architecture and Building Systems
Author-email: cea@arch.ethz.ch
License: MIT
Platform: UNKNOWN
